odoo9_addon_openeducat_scholarship-9.0.2.4.0-py2.7-nspkg.pth
odoo_addons/openeducat_scholarship/__openerp__.py
odoo_addons/openeducat_scholarship/__init__.py
odoo_addons/openeducat_scholarship/scholarship_menu.xml
odoo_addons/openeducat_scholarship/security/ir.model.access.csv
odoo_addons/openeducat_scholarship/models/scholarship.py
odoo_addons/openeducat_scholarship/models/scholarship_type.py
odoo_addons/openeducat_scholarship/models/__init__.py
odoo_addons/openeducat_scholarship/i18n/openeducat_scholarship.pot
odoo_addons/openeducat_scholarship/views/scholarship_type_view.xml
odoo_addons/openeducat_scholarship/views/scholarship_view.xml
odoo_addons/openeducat_scholarship/demo/op.scholarship.csv
odoo_addons/openeducat_scholarship/demo/op.scholarship.type.csv
odoo_addons/openeducat_scholarship/static/description/scholarship.png
odoo_addons/openeducat_scholarship/static/description/openeducat_logo.png
odoo_addons/openeducat_scholarship/static/description/index.html
odoo_addons/openeducat_scholarship/static/description/icon.png
odoo_addons/openeducat_scholarship/static/description/openeducat_scholarship_banner.jpg
odoo9_addon_openeducat_scholarship-9.0.2.4.0.dist-info/top_level.txt
odoo9_addon_openeducat_scholarship-9.0.2.4.0.dist-info/WHEEL
odoo9_addon_openeducat_scholarship-9.0.2.4.0.dist-info/RECORD
odoo9_addon_openeducat_scholarship-9.0.2.4.0.dist-info/metadata.json
odoo9_addon_openeducat_scholarship-9.0.2.4.0.dist-info/DESCRIPTION.rst
odoo9_addon_openeducat_scholarship-9.0.2.4.0.dist-info/METADATA
odoo9_addon_openeducat_scholarship-9.0.2.4.0.dist-info/namespace_packages.txt
